<mxGraphModel dx="800" dy="800" grid="1" guides="1" tooltips="1" connect="1" fold="1" page="1" pageScale="1" pageWidth="826" pageHeight="1169" style="default-style2"><root><mxCell id="0"/><mxCell id="1" parent="0"/><mxCell id="2" value="&lt;table style=&quot;font-size: 1em; color=#666666;width: 100%; height: 100%;&quot; border=&quot;0&quot; cellspacing=&quot;0&quot; cellpadding=&quot;0&quot;&gt;&lt;tbody&gt;&lt;tr&gt;&lt;td width=&quot;60&quot;&gt;&amp;nbsp;&lt;/td&gt;&lt;td align=&quot;left&quot; height=&quot;50&quot;&gt;Drill Calendar&lt;/td&gt;&lt;/tr&gt;&lt;tr&gt;&lt;td width=&quot;60&quot;&gt;&amp;nbsp;&lt;/td&gt;&lt;td width=&quot;80&quot;&gt;&amp;nbsp;&lt;/td&gt;&lt;td align=&quot;left&quot; height=&quot;50&quot;&gt;http://localhost:8000/index.html&lt;/td&gt;&lt;/tr&gt;&lt;tr&gt;&lt;td height=&quot;100%&quot;&gt;&amp;nbsp;&lt;/td&gt;&lt;/tr&gt;&lt;/tbody&gt;&lt;/table&gt;" style="strokeWidth=1;shape=mxgraph.mockup.containers.browserWindow;strokeColor=#666666;strokeColor2=#008cff;strokeColor3=#c4c4c4;textColor=#666666;fillColor=#ffffff;mainText=,;html=1;fontSize=17;fontColor=#666666;overflow=fill;" vertex="1" parent="1"><mxGeometry x="10" y="10" width="810" height="1150" as="geometry"/></mxCell><mxCell id="3" value="" style="verticalLabelPosition=bottom;verticalAlign=top;strokeWidth=1;shape=mxgraph.mockup.forms.calendar;strokeColor=#999999;strokeColor2=#008cff;mainText=April 2013;textSize=12;textColor=#999999;firstDay=0;startOn=0;days=30;prevDays=31;dayNames=Mo,Tu,We,Th,Fr,Sa,Su;selDay=24;textColor2=#ffffff;" vertex="1" parent="1"><mxGeometry x="30" y="140" width="770" height="1000" as="geometry"/></mxCell><mxCell id="4" value="" style="verticalLabelPosition=bottom;verticalAlign=top;strokeWidth=1;shape=mxgraph.mockup.forms.horSlider;strokeColor=#999999;fillColor=#ffffff;sliderStyle=basic;sliderPos=20;handleStyle=circle;fillColor2=#ddeeff;" vertex="1" parent="1"><mxGeometry x="90" y="500" width="70" height="10" as="geometry"/></mxCell><mxCell id="5" value="" style="verticalLabelPosition=bottom;verticalAlign=top;strokeWidth=1;shape=mxgraph.mockup.forms.horSlider;strokeColor=#999999;fillColor=#ffffff;sliderStyle=basic;sliderPos=20;handleStyle=circle;fillColor2=#ddeeff;" vertex="1" parent="1"><mxGeometry x="190" y="500" width="70" height="10" as="geometry"/></mxCell><mxCell id="6" value="" style="verticalLabelPosition=bottom;verticalAlign=top;strokeWidth=1;shape=mxgraph.mockup.forms.horSlider;strokeColor=#999999;fillColor=#ffffff;sliderStyle=basic;sliderPos=20;handleStyle=circle;fillColor2=#ddeeff;" vertex="1" parent="1"><mxGeometry x="280" y="500" width="70" height="10" as="geometry"/></mxCell><mxCell id="7" value="" style="verticalLabelPosition=bottom;verticalAlign=top;strokeWidth=1;shape=mxgraph.mockup.forms.horSlider;strokeColor=#999999;fillColor=#ffffff;sliderStyle=basic;sliderPos=20;handleStyle=circle;fillColor2=#ddeeff;" vertex="1" parent="1"><mxGeometry x="380" y="500" width="70" height="10" as="geometry"/></mxCell><mxCell id="8" value="" style="verticalLabelPosition=bottom;verticalAlign=top;strokeWidth=1;shape=mxgraph.mockup.forms.horSlider;strokeColor=#999999;fillColor=#ffffff;sliderStyle=basic;sliderPos=20;handleStyle=circle;fillColor2=#ddeeff;" vertex="1" parent="1"><mxGeometry x="470" y="500" width="70" height="10" as="geometry"/></mxCell><mxCell id="20" value="" style="verticalLabelPosition=bottom;verticalAlign=top;strokeWidth=1;shape=mxgraph.mockup.forms.horSlider;strokeColor=#999999;fillColor=#ffffff;sliderStyle=basic;sliderPos=20;handleStyle=circle;fillColor2=#ddeeff;" vertex="1" parent="1"><mxGeometry x="670" y="500" width="70" height="10" as="geometry"/></mxCell><mxCell id="21" value="" style="verticalLabelPosition=bottom;verticalAlign=top;strokeWidth=1;shape=mxgraph.mockup.forms.horSlider;strokeColor=#999999;fillColor=#ffffff;sliderStyle=basic;sliderPos=20;handleStyle=circle;fillColor2=#ddeeff;" vertex="1" parent="1"><mxGeometry x="570" y="500" width="70" height="10" as="geometry"/></mxCell></root></mxGraphModel>